.gitattributes
.gitignore
LICENSE.txt
MANIFEST.in
README.md
logo.png
logo2.png
requirements.txt
setup.py
tox.ini
update_version.sh
.github/workflows/build.yml
.github/workflows/docs.yml
.github/workflows/publish-docs.yml
docs/au.rst
docs/automation.rst
docs/conf.py
docs/costfunctions.rst
docs/customcf.rst
docs/dev.rst
docs/frontend.rst
docs/index.rst
docs/install.rst
docs/requirements.txt
docs/routines.rst
docs/running.rst
docs/_templates/sidebar_links.html
docs/images/devoverview.png
docs/images/link_paper.png
docs/images/routine1.png
docs/images/routine2.png
docs/images/routine3.png
docs/images/routine4.png
docs/images/routine5.png
docs/images/running1.png
docs/images/running2.png
docs/images/toc_graphic_alt.png
nmrpoise/.DS_Store
nmrpoise/__init__.py
nmrpoise/_version.py
nmrpoise/poise.py
nmrpoise/topspin_install.py
nmrpoise.egg-info/PKG-INFO
nmrpoise.egg-info/SOURCES.txt
nmrpoise.egg-info/dependency_links.txt
nmrpoise.egg-info/entry_points.txt
nmrpoise.egg-info/requires.txt
nmrpoise.egg-info/top_level.txt
nmrpoise/__pycache__/__init__.cpython-310.pyc
nmrpoise/__pycache__/__init__.cpython-36.pyc
nmrpoise/__pycache__/__init__.cpython-37.pyc
nmrpoise/__pycache__/__init__.cpython-38.pyc
nmrpoise/__pycache__/__init__.cpython-39.pyc
nmrpoise/au/poise_1d
nmrpoise/au/poise_1d_noapk
nmrpoise/au/poise_2d
nmrpoise/au/poise_psyche
nmrpoise/au/poisecal
nmrpoise/poise_backend/__init__.py
nmrpoise/poise_backend/backend.py
nmrpoise/poise_backend/cfhelpers.py
nmrpoise/poise_backend/costfunctions.py
nmrpoise/poise_backend/costfunctions_user.py
nmrpoise/poise_backend/get_cfs.py
nmrpoise/poise_backend/optpoise.py
nmrpoise/poise_backend/shared.py
nmrpoise/poise_backend/__pycache__/__init__.cpython-310.pyc
nmrpoise/poise_backend/__pycache__/__init__.cpython-36.pyc
nmrpoise/poise_backend/__pycache__/__init__.cpython-37.pyc
nmrpoise/poise_backend/__pycache__/__init__.cpython-38.pyc
nmrpoise/poise_backend/__pycache__/__init__.cpython-39.pyc
nmrpoise/poise_backend/__pycache__/backend.cpython-310.pyc
nmrpoise/poise_backend/__pycache__/backend.cpython-36.pyc
nmrpoise/poise_backend/__pycache__/backend.cpython-37.pyc
nmrpoise/poise_backend/__pycache__/backend.cpython-38.pyc
