Metadata-Version: 2.1
Name: nmrpoise
Version: 1.2.3
Summary: Parameter Optimisation by Iterative Spectral Evaluation, a TopSpin-compatible NMR package
Home-page: https://github.com/foroozandehgroup/nmrpoise
Author: Jonathan Yong
Author-email: jonathan.yong@chem.ox.ac.uk
License: UNKNOWN
Platform: UNKNOWN
Classifier: Programming Language :: Python :: 3.6
Classifier: Programming Language :: Python :: 3.7
Classifier: Programming Language :: Python :: 3.8
Classifier: License :: OSI Approved :: GNU General Public License v3 or later (GPLv3+)
Classifier: Operating System :: OS Independent
Requires-Python: >=3.6
License-File: LICENSE.txt
